{"7tplff1Q8IdQtSQYbjxSIQ==":"abarrotesfe-960x952.jpg","aQd1g3eDyZA3m4KE5u1xRw==":"abarrotes-480x270.jpg","n0J/7jBrlxQIFOfv14laFg==":"producto-960x540.jpg","bT/4ChzJc2lhIo1LGUbxVQ==":"abarrotesfe-1-960x952.jpg","SS5ifaJIzsNWIC5+uMibSw==":"eventos-588x580.jpg","ly2S5esSxJC68D/H7uaJwg==":"sabritas-512x294.png","gK5uFcFIdIWu+zb+5+100A==":"abarrotesfe-96x95.jpg","KO23sRkYiwoQ/C2WYNq5qQ==":"fruter%C3%ADa-696x365.jpg","jjD6BgpAu/jkRCbh+FVCXA==":"bebidas-275x183.jpg","SCrWzZs/qI3nwFFc96CP/w==":"abarrotesfe-561x556.jpg","RHzYfaD2bN8lTEJhoO0iQQ==":"abarrotesfe-561x556.jpeg","EkYccFkCRTNpOhuoRHGexA==":"abarrotes-480x270.jpeg","G+aLOFB+62IGXs1AM24OJA==":"abarrotesfe-1-561x556.jpeg","jQ7l2X2oJPGzJ/VTzdikkg==":"abarrotesfe-2-561x556.jpeg","k8ppx6YGeEqPM2ZyjgdEZg==":"abarrotesfe-3-561x556.jpeg","7ASPviUHSsDqiOun0Fpd5g==":"abarrotesfe-4-561x556.jpeg","NWZ7kOBBzIkZx4iByn2CSw==":"producto-561x316.jpg","c6/bKTeDx0wzJo3qDyL5vw==":"eventos-561x553.jpg","gRuxlwMn2rsNpLTAv0W9sw==":"eventos-561x553.jpeg","ykfhNbxZOob0SmU6XzJ9yA==":"bebidas-275x183.jpeg","PSPmyybgecgKlE309obVHg==":"sabritaso-696x696.jpg","cTe+oBRMz4d4L5DUux4C/w==":"takis-696x696.jpg","ck2xo5q8D8gufk6dkQVAwQ==":"ping%C3%BCinos-515x515.jpg","JaEJtKkZRGwwMfBIqV0ygg==":"mar%C3%ADas-696x696.jpg","AnAYv1Gz9Yc4Su20QeAdbw==":"paletapayaso-696x696.jpg","NlEo9r4D2K+fvH8bMtM5aQ==":"mentos-500x500.jpg","0o3wx3U7p82zLcFMY8aNPQ==":"cebolla-696x696.jpg","G2NRaW0euBTXrfS/fm2ssQ==":"chile-696x696.jpg","nvzYUF6wZs0c2Xo4UM0wmQ==":"huevo-594x452.jpg","C4IbIcjSxPB0+KM9r0gtBg==":"jitomate-696x696.jpg","j2iFluQWQO2NKKdDSrb/1g==":"lim%C3%B3n-696x696.jpg","KO7uvehdsuU+BOpp62K4nA==":"platano-696x696.jpg","To3vTHTtRUIFzGFNMastcQ==":"coca-cola-240x240.jpg","AgnZBs0VPJM2oOMyr/tTwA==":"gatorade-540x540.jpg","9Dqpfiu2Z4gKk6bG6Dstlw==":"jugo-696x696.jpg","fSZBDJHASY9sfOYee+Favw==":"leche-696x696.jpg","5Yt18FLbyC+GenJw+fBypw==":"pe%C3%B1afiel-515x515.jpg","EJBZvQc4bC7HsUmYEcglSA==":"bonafont-400x400.jpg"}